sphinx_preview/__init__.py
sphinx_preview/assets/sphinx_preview.css
sphinx_preview/assets/template_sphinx_preview.js
sphinx_preview/sphinx_preview.py
sphinx_preview/version.py
sphinx_preview-0.1.2.dist-info/LICENSE
sphinx_preview-0.1.2.dist-info/WHEEL
sphinx_preview-0.1.2.dist-info/METADATA
sphinx_preview-0.1.2.dist-info/RECORD
